immunity_users/__init__.py
immunity_users/admin.py
immunity_users/apps.py
immunity_users/backends.py
immunity_users/middleware.py
immunity_users/mixins.py
immunity_users/models.py
immunity_users/multitenancy.py
immunity_users/password_validation.py
immunity_users/settings.py
immunity_users/tasks.py
immunity_users/utils.py
immunity_users/views.py
immunity_users/widgets.py
immunity_users/accounts/__init__.py
immunity_users/accounts/adapter.py
immunity_users/accounts/urls.py
immunity_users/accounts/views.py
immunity_users/accounts/locale/de/LC_MESSAGES/django.po
immunity_users/accounts/locale/fur/LC_MESSAGES/django.po
immunity_users/accounts/locale/it/LC_MESSAGES/django.po
immunity_users/accounts/locale/ru/LC_MESSAGES/django.po
immunity_users/accounts/locale/sl/LC_MESSAGES/django.po
immunity_users/accounts/static/openwisp-users/accounts/css/change-password.css
immunity_users/accounts/templates/account/email_confirm.html
immunity_users/accounts/templates/account/email_verification_success.html
immunity_users/accounts/templates/account/login.html
immunity_users/accounts/templates/account/logout_success.html
immunity_users/accounts/templates/account/password_change.html
immunity_users/accounts/templates/account/password_change_success.html
immunity_users/accounts/templates/account/password_not_required.html
immunity_users/accounts/templates/account/email/base_message.txt
immunity_users/accounts/templates/account/email/email_confirmation_message.html
immunity_users/accounts/templates/account/email/email_confirmation_message.txt
immunity_users/accounts/templates/account/email/email_confirmation_signup_message.html
immunity_users/accounts/templates/account/email/password_expiration_message.html
immunity_users/accounts/templates/account/email/password_expiration_message.txt
immunity_users/accounts/templates/allauth/layouts/base.html
immunity_users/api/__init__.py
immunity_users/api/authentication.py
immunity_users/api/filters.py
immunity_users/api/mixins.py
immunity_users-1.1.0.dist-info/LICENSE
immunity_users-1.1.0.dist-info/METADATA
immunity_users-1.1.0.dist-info/WHEEL
immunity_users-1.1.0.dist-info/top_level.txt
immunity_users-1.1.0.dist-info/RECORD
