Metadata-Version: 2.1
Name: immunity-users
Version: 1.1.0
Summary: Provides basic multi-tenancy features for OpenWISP (using the Django web-framework)
Home-page: http://openwisp.org
Author: OpenWISP
Author-email: support@openwisp.io
License: BSD
Download-URL: https://github.com/edge-servers/immunity-users/releases
Keywords: openwisp,django,organizations,users
Platform: Platform Independent
Classifier: Development Status :: 5 - Production/Stable
Classifier: Environment :: Web Environment
Classifier: Topic :: Internet :: WWW/HTTP
Classifier: Intended Audience :: Developers
Classifier: License :: OSI Approved :: BSD License
Classifier: Operating System :: OS Independent
Classifier: Framework :: Django
Classifier: Programming Language :: Python :: 3
License-File: LICENSE
Requires-Dist: django-allauth[socialaccount]~=0.63.6
Requires-Dist: django-extensions~=3.2.3
Requires-Dist: django-organizations~=2.4.1
Requires-Dist: django-phonenumber-field~=8.0.0
Requires-Dist: django-sesame~=3.2.2
Requires-Dist: openwisp-utils[celery,rest]~=1.1.0
Requires-Dist: packaging
Requires-Dist: phonenumbers~=8.13.44
